ArticleSumm/__init__.py
articlesumm-0.0.2.dist-info/LICENSE.txt
articlesumm-0.0.2.dist-info/METADATA
articlesumm-0.0.2.dist-info/WHEEL
articlesumm-0.0.2.dist-info/top_level.txt
articlesumm-0.0.2.dist-info/RECORD
