Metadata-Version: 2.1
Name: articlesumm
Version: 0.0.2
Summary: Custom scientific/research article summarization library based on Statistical features
Home-page: 
Author: Maxwell Tetteh
Author-email: tettehmaxwell11@gmail.com
License: MIT
Keywords: text summarization,scientific articles
Classifier: Development Status :: 5 - Production/Stable
Classifier: Intended Audience :: Education
Classifier: Operating System :: Microsoft :: Windows :: Windows 10
Classifier: License :: OSI Approved :: MIT License
Classifier: Programming Language :: Python :: 3
License-File: LICENSE.txt
Requires-Dist: requests (>=2.26.0)
Requires-Dist: nltk (>=3.6.5)
